cli/__init__.py
cli/api.py
cli/auth.py
cli/cache.py
cli/cli.py
cli/config.py
cli/consent.py
cli/gcloud.py
cli/upload.py
cli/dbedit/__init__.py
cli/dbedit/cli.py
cli/dbedit/config.py
cli/dbedit/core.py
cli/dbedit/list.py
cli/dbedit/remove.py
tests/__init__.py
tests/conftest.py
tests/test_api.py
tests/test_auth.py
tests/test_cache.py
tests/test_cli.py
tests/test_upload.py
tests/util.py
tests/dbedit/__init__.py
tests/dbedit/constants.py
tests/dbedit/test_core.py
tests/dbedit/test_list.py
tests/dbedit/test_remove.py
cidc_cli-0.10.2.dist-info/LICENSE
cidc_cli-0.10.2.dist-info/METADATA
cidc_cli-0.10.2.dist-info/WHEEL
cidc_cli-0.10.2.dist-info/entry_points.txt
cidc_cli-0.10.2.dist-info/top_level.txt
cidc_cli-0.10.2.dist-info/RECORD
