Metadata-Version: 2.1
Name: cidc-cli
Version: 0.10.2
Summary: A command-line interface for interacting with the CIDC.
Requires-Python: >=3.6
License-File: LICENSE
Requires-Dist: click (~=8.0.1)
Requires-Dist: cloud-sql-python-connector[pg8000]
Requires-Dist: pandas (==1.2.4)
Requires-Dist: python-dotenv (==0.10.3)
Requires-Dist: python-jose (==3.0.1)
Requires-Dist: pyperclip (==1.8.0)
Requires-Dist: requests (==2.22.0)
Requires-Dist: sqlalchemy (~=1.4.0)
